xdrl/__init__.py
xdrl/core.py
xdrl-0.1.0.dist-info/licenses/LICENSE
xdrl-0.1.0.dist-info/METADATA
xdrl-0.1.0.dist-info/WHEEL
xdrl-0.1.0.dist-info/top_level.txt
xdrl-0.1.0.dist-info/RECORD
