Metadata-Version: 2.4
Name: xdrl
Version: 0.1.0
Summary: Explainability for deep RL.
Author-email: Yoann Poupart <yoann.poupart@ens-lyon.org>
License: MIT License
Project-URL: homepage, https://xdrl.readthedocs.io/
Project-URL: documentation, https://xdrl.readthedocs.io/
Project-URL: source, https://github.com/Xmaster6y/xdrl
Project-URL: issues, https://github.com/Xmaster6y/xdrl/issues
Project-URL: releasenotes, https://github.com/Xmaster6y/xdrl/releases
Classifier: Development Status :: 3 - Alpha
Classifier: Intended Audience :: Science/Research
Classifier: Programming Language :: Python :: 3
Classifier: Programming Language :: Python :: 3.10
Classifier: Programming Language :: Python :: 3.11
Classifier: Programming Language :: Python :: 3.12
Requires-Python: >=3.11
License-File: LICENSE
Dynamic: license-file
